example_qspec/__init__.py
example_qspec/quant_spec_vi.py
example_qspec-0.1.0.dist-info/METADATA
example_qspec-0.1.0.dist-info/WHEEL
example_qspec-0.1.0.dist-info/licenses/LICENSE
example_qspec-0.1.0.dist-info/RECORD
