Metadata-Version: 2.1
Name: example_qspec
Version: 0.1.0
Summary: A small example package
Author-email: Example Author <author@example.com>
License: MIT License
Classifier: License :: OSI Approved :: MIT License
Classifier: Operating System :: OS Independent
Classifier: Programming Language :: Python :: 3
Requires-Python: >=3.7
Requires-Dist: matplotlib
Requires-Dist: numpy
Requires-Dist: pandas
Requires-Dist: scipy
Requires-Dist: tensorflow-probability>=0.16.0
Requires-Dist: tensorflow>=2.8.0
